y2b_download.py
y2b_playlist.py
y2b-0.2.0.dist-info/LICENSE
y2b-0.2.0.dist-info/METADATA
y2b-0.2.0.dist-info/WHEEL
y2b-0.2.0.dist-info/entry_points.txt
y2b-0.2.0.dist-info/top_level.txt
y2b-0.2.0.dist-info/RECORD
